LICENSE
audiocodes_exporter/cli.py
audiocodes_exporter/collector.py
audiocodes_exporter/collectors/call_stats_collector.py
audiocodes_exporter/collectors/cluster_stats_collector.py
audiocodes_exporter/collectors/coder_stats_collector.py
audiocodes_exporter/collectors/cpu_stats_collector.py
audiocodes_exporter/collectors/ddos_stats_collector.py
audiocodes_exporter/collectors/dsp_stats_collector.py
audiocodes_exporter/collectors/ha_stats_collector.py
audiocodes_exporter/collectors/license_stats_collector.py
audiocodes_exporter/collectors/media_stats_collector.py
audiocodes_exporter/collectors/other_stats_collector.py
audiocodes_exporter/collectors/port_stats_collector.py
audiocodes_exporter/collectors/siprec_stats_collector.py
audiocodes_exporter/collectors/status_collector.py
audiocodes_exporter/collectors/storage_stats_collector.py
audiocodes_exporter/collectors/system_stats_collector.py
audiocodes_exporter/helpers.py
audiocodes_exporter-0.1.5.dist-info/entry_points.txt
audiocodes_exporter-0.1.5.dist-info/LICENSE
audiocodes_exporter-0.1.5.dist-info/WHEEL
audiocodes_exporter-0.1.5.dist-info/METADATA
audiocodes_exporter-0.1.5.dist-info/RECORD
